LICENSE
MANIFEST.in
README.rst
hypothesis_fspaths.py
setup.cfg
setup.py
hypothesis_fspaths.egg-info/PKG-INFO
hypothesis_fspaths.egg-info/SOURCES.txt
hypothesis_fspaths.egg-info/dependency_links.txt
hypothesis_fspaths.egg-info/requires.txt
hypothesis_fspaths.egg-info/top_level.txt
tests/__init__.py
tests/test_fspaths.py